setup.py
cloudcode/__init__.py
cloudcode/authorization.py
cloudcode/cloudcode.py
cloudcode/context.py
cloudcode/utils.py
leancloud_cloudcode_sdk.egg-info/PKG-INFO
leancloud_cloudcode_sdk.egg-info/SOURCES.txt
leancloud_cloudcode_sdk.egg-info/dependency_links.txt
leancloud_cloudcode_sdk.egg-info/requires.txt
leancloud_cloudcode_sdk.egg-info/top_level.txt