Metadata-Version: 1.1
Name: leancloud-cloudcode-sdk
Version: 1.0.0
Summary: LeanCloud Cloudcode Python SDK
Home-page: https://leancloud.cn/
Author: asaka
Author-email: lan@leancloud.rocks
License: LGPL
Keywords: Leancloud SDK
Platform: UNKNOWN
Classifier: Development Status :: 3 - Alpha
Classifier: Intended Audience :: Developers
Classifier: Programming Language :: Python :: 2
Classifier: Programming Language :: Python :: 2.6
Classifier: Programming Language :: Python :: 2.7
